Workbook

Sheet Questions
A1: Day | B1: Question | C1: Category | D1: Why This Works | E1: Builds On | F1: AI Reflection Seed
A2: 1 | B2: If your life had a theme song that played every time you walked into a room, what would it be? | C2: Identity | D2: Music choices reveal emotional self-image without asking directly | F2: Track how self-image evolves. Does their song choice shift over months?
A3: 2 | B3: What's something you believe that most people you know would disagree with? | C3: Values | D3: Surfaces conviction vs conformity. The answer AND the hesitation matter. | F3: Note which beliefs they hold tightly vs loosely over time
A4: 3 | B4: You get one meal, forever. Every dinner for the rest of your life. What is it? | C4: Preferences | D4: Constraint reveals priority. Comfort vs adventure vs nostalgia. | F4: Callback fuel — "You chose ___ on Day 3. Still your forever meal?"
A5: 4 | B5: What's something you used to be absolutely sure about but aren't anymore? | C5: Growth | D5: Directly surfaces self-awareness about change. Early growth baseline. | F5: Core growth marker. Revisit at Day 60, 120.
A6: 5 | B6: If you could have dinner with anyone, dead or alive — but you can't ask them any questions, you can only listen — who do you pick? | C6: Curiosity | D6: Twist on the classic. Removes performance, reveals who they genuinely want to learn from. | F6: Who they want to listen to says more than who they want to impress
A7: 6 | B7: What's the most recent thing that made you laugh until you couldn't breathe? | C7: Joy | D7: Humor = values + worldview. Totally disarming. | F7: Track joy patterns — what consistently makes them laugh?
A8: 7 | B8: What's a hill you will absolutely die on that is completely stupid? | C8: Personality | D8: Permission to be irrational and passionate. Week 1 capstone — they're comfortable now. | F8: The silly hills often connect to real values underneath
A9: 8 | B9: What's the best advice you've ever ignored? | C9: Wisdom | D9: Reveals the gap between knowing and doing. Very human. | E9: Day 4 | F9: Compare with Day 4 — are their certainty-shifts and ignored-advice related?
A10: 9 | B10: If you had to describe yourself using only three questions (not answers), what would they be? | C10: Self-Knowledge | D10: Meta-question. The questions they ask reveal what they think matters. | F10: These three questions become a personal compass to revisit
A11: 10 | B11: What do you think your 80-year-old self would want to tell you right now? | C11: Time | D11: Future self as advisor. Surfaces what they suspect they're getting wrong. | E11: Day 4 | F11: Pair with Day 4 (what they stopped believing) for growth trajectory
A12: 11 | B12: Who in your life makes you feel most like yourself? | C12: Relationships | D12: Not "who do you love most" — who lets you be you. Different answer. | F12: Track relationship references across answers. Who keeps appearing?
A13: 12 | B13: What would you do with your life if money was irrelevant and nobody would judge you? | C13: Purpose | D13: Removes the two biggest constraints. What's left is close to the truth. | F13: Compare with what they actually do. The gap is the story.
A14: 13 | B14: What's a small, everyday thing that you think is genuinely beautiful? | C14: Attention | D14: What you find beautiful reveals where you pay attention. Philosophy 101. | F14: Build a collection of their beautiful things over months
A15: 14 | B15: If your younger self could see your life right now, what would surprise them most? | C15: Growth | D15: Week 2 capstone. Bridges past and present self. | E15: Day 4, Day 10 | F15: Triangulate: past certainties, current doubts, younger self's surprise
A16: 15 | B16: What's something you're afraid of that has nothing to do with physical danger? | C16: Fear | D16: Emotional/existential fear. Vulnerability spike — they're ready by now. | F16: Fears reveal values. What you're afraid to lose = what matters most.
A17: 16 | B17: Is there something you keep almost saying to someone but never do? (You don't have to say what — just who, and why you haven't.) | C17: Relationships | D17: Permission to be vague. The restraint itself is the data. | E17: Day 11 | F17: Unsaid things are load-bearing walls in someone's emotional architecture
A18: 17 | B18: You find a wallet with $2,000 and an ID. You're broke. No cameras. No one will ever know. What do you actually do? | C18: Ethics | D18: Not what SHOULD you do. What WOULD you do. The honesty matters more than the answer. | F18: Frame reflection around the gap (or alignment) between should and would
A19: 18 | B19: What's something you spend time on that you can't really justify but refuse to give up? | C19: Authenticity | D19: The unjustifiable things are often the most real. | E19: Day 12 | F19: Compare with Day 12 (no judgment/money). Are these the same things?
A20: 19 | B20: If you could know the absolute truth about one thing, what would you want to know? | C20: Curiosity | D20: Reveals their deepest question. Some will go cosmic, some personal. | E20: Day 5 | F20: The question they'd ask the universe vs who they'd listen to (Day 5)
A21: 20 | B21: What do you think happens after we die? And how much does your answer affect how you live? | C21: Mortality | D21: The big one. But the second half is the real question. | F21: How belief about death shapes life choices. Core philosophical territory.
A22: 21 | B22: What's something you've done that you're proud of that nobody else knows about or would care about? | C22: Self-Worth | D22: Week 3 capstone. Pride without audience = intrinsic values. | E22: Day 13 | F22: Private pride + private beauty (Day 13) = their inner world's blueprint
A23: 22 | B23: If your life so far was a book, what would this chapter be called? | C23: Narrative | D23: Story-making. How they frame their current moment. | F23: Revisit every 90 days. Chapter titles track life transitions.
A24: 23 | B24: What's a question nobody has ever asked you that you wish someone would? | C24: Depth | D24: They write their own question. Often the most revealing answer of all. | E24: Day 9 | F24: Compare with Day 9's self-description questions. Convergence = self-knowledge.
A25: 24 | B25: Do you think you're living the life you were meant to live, or the one you ended up in? | C25: Agency | D25: Meant vs ended-up. Fate vs choice. No wrong answer, only honest ones. | E25: Day 12 | F25: Layer with Day 12 (no constraints) and Day 10 (80-year-old advice)
A26: 25 | B26: What would you want someone to say about you at your funeral that isn't true yet? | C26: Aspiration | D26: The gap between who you are and who you want to become. | E26: Day 14 | F26: This IS their growth edge. Revisit at 90, 180 days.
A27: 26 | B27: Is there a version of yourself you've outgrown but kind of miss? | C27: Change | D27: Nostalgia for shed selves. Growth has costs. | E27: Day 4, Day 14 | F27: Past beliefs + younger self + outgrown versions = identity archaeology
A28: 27 | B28: What's the most important thing you've changed your mind about in the last year? | C28: Growth | D28: Concrete, recent. Evidence they're still evolving. | E28: Day 4 | F28: Day 4 was lifetime. Day 27 is this year. Track the pace of change.
A29: 28 | B29: If you could send a one-sentence message to everyone on Earth, what would you say? | C29: Values | D29: Universal message reveals core values distilled. | E29: Day 2 | F29: Compare with Day 2's contrarian belief. Public message vs private conviction.
A30: 29 | B30: Looking at your answers from this month — what surprised you? | C30: Reflection | D30: First meta-moment. They review their own portrait. | E30: All | F30: AI reflection here: synthesize patterns, growth, contradictions WITH WARMTH.
A31: 30 | B31: What question do you want to wake up to tomorrow? | C31: Agency | D31: They design their own Day 31. The student becomes the philosopher. | E31: All | F31: Use their question. They're co-creating the experience now.
B32: "If your life had a loading screen, what 'helpful tip' would it show?
B33: What’s a tiny moment from your life that still glows like it got struck by secret lightning?
B34: If your shadow could leave you one note on the kitchen table, what do you think it would say?
B35: Do you think time ever laughs at how seriously we take Tuesdays?
B36: If your memories had weather, what season keeps showing up the most?
B37: If your childhood self could review your life so far, what would they give extra points for?
B38: If your soul had pockets, what random little things do you think it keeps in there?

Sheet Categories
A1: Category | B1: Count | C1: Philosophy Connection | D1: Emotional Temperature
A2: Identity | B2: =COUNTIF(Questions!C:C,A2) -> 1 | C2: Know thyself (Socrates) | D2: Warm
A3: Values | B3: =COUNTIF(Questions!C:C,A3) -> 2 | C3: Ethics, moral philosophy | D3: Medium
A4: Preferences | B4: =COUNTIF(Questions!C:C,A4) -> 1 | C4: Aesthetics, phenomenology | D4: Low
A5: Growth | B5: =COUNTIF(Questions!C:C,A5) -> 3 | C5: Dialectics, becoming | D5: Medium
A6: Curiosity | B6: =COUNTIF(Questions!C:C,A6) -> 2 | C6: Epistemology, wonder | D6: Low-medium
A7: Joy | B7: =COUNTIF(Questions!C:C,A7) -> 1 | C7: Hedonic philosophy, flourishing | D7: Low
A8: Personality | B8: =COUNTIF(Questions!C:C,A8) -> 1 | C8: Authenticity (Sartre) | D8: Low
A9: Wisdom | B9: =COUNTIF(Questions!C:C,A9) -> 1 | C9: Practical philosophy | D9: Medium
A10: Self-Knowledge | B10: =COUNTIF(Questions!C:C,A10) -> 1 | C10: Metacognition, examined life | D10: Medium-high
A11: Time | B11: =COUNTIF(Questions!C:C,A11) -> 1 | C11: Temporal philosophy, mortality | D11: Medium-high
A12: Relationships | B12: =COUNTIF(Questions!C:C,A12) -> 2 | C12: Buber, intersubjectivity | D12: High
A13: Purpose | B13: =COUNTIF(Questions!C:C,A13) -> 1 | C13: Existentialism, telos | D13: High
... A21: Depth | B21: =COUNTIF(Questions!C:C,A21) -> 1 | C21: Questioning (Gadamer) | D21: High
A22: Agency | B22: =COUNTIF(Questions!C:CC,A22) -> 2 | C22: Free will, determinism | D22: High
A23: Aspiration | B23: =COUNTIF(Questions!C:C,A23) -> 1 | C23: Virtue ethics, eudaimonia | D23: High
A24: Change | B24: =COUNTIF(Questions!C:C,A24) -> 1 | C24: Heraclitus, impermanence | D24: Medium
A25: Reflection | B25: =COUNTIF(Questions!C:C,A25) -> 1 | C25: The examined life (Socrates) | D25: High

Sheet Arc Design
A1: Week | B1: Theme | C1: Emotional Range | D1: Design Intent
A2: 1 | B2: The Warm-Up | C2: Light > Comfortable | D2: Build trust. Low stakes, high charm. They should be smiling and slightly surprised by how honest they're being.
A3: 2 | B3: Going Deeper | C3: Comfortable > Reflective | D3: Relationships, time, the self. They start noticing they're thinking about these questions after they answer.
A4: 3 | B4: The Uncomfortable Middle | C4: Reflective > Vulnerable | D4: Ethics, fear, mortality. The questions they'll think about at 2am. But they're ready because Week 1-2 built trust.
A5: 4 | B5: Integration | C5: Vulnerable > Empowered | D5: Meaning-making. The portrait emerges. They see themselves. Day 30 hands them the pen.

Sheet Cost Architecture
A1: Component | B1: Strategy | C1: Tokens Per User/Month | D1: Cost Estimate
B2: COMPRESSION ARCHITECTURE
A3: Principle | B3: Compress the language, never compress the meaning. Proper nouns and formative details always survive.
B5: DAILY PROCESSING
A6: Question Delivery | B6: Pre-written, no AI needed. SMS via Twilio. | C6: 0 | D6: $0.01-0.05/msg
A7: Response Ingestion | B7: Store raw text in DB. No AI at reply time. | C7: 0 | D7: DB storage only
A8: Micro-Summary (per reply) | B8: Haiku writes 1-2 sentence summary preserving proper nouns, relationships, and formative details. Replaces tags.
A9: Light user (~50% reply rate) | B9: ~40 tokens out per reply, ~60 replies/mo | C9: ~4,800/mo | D9: $0.01/mo
A10: Heavy user (daily, verbose) | B10: ~80 tokens out per reply, ~30 replies/mo... wait, 120/mo | C10: ~9,600/mo | D10: $0.03/mo
B12: WEEKLY PROCESSING
A13: Week Card | B13: Haiku reads 7 micro-summaries, writes a short paragraph. Preserves specific references (names, places, events).
A14: Light user | B14: ~150 tokens per card, ~2-3 cards/mo | C14: ~1,200/mo | D14: $0.02/mo
A15: Heavy user | B15: ~250 tokens per card, ~4 cards/mo | C15: ~4,250/mo | D15: $0.04/mo
B17: MONTHLY PROCESSING
A18: Monthly Portrait (Day 29) | B18: Sonnet reads month's week cards + micro-summaries. Generates personalized reflection.
A19: Light user | B19: Reads ~3K context, generates ~300 tokens | C19: ~3,500 | D19: $0.02/mo
A20: Heavy user | B20: Reads ~8K context, generates ~500 tokens | C20: ~8,500 | D20: $0.06/mo
B22: QUARTERLY PROCESSING
A23: Quarterly Arc | B23: Sonnet reads 3 monthly portraits. Surfaces growth patterns across the season.
A24: Light user | B24: Reads ~1K, generates ~400 | C24: ~1,400/qtr | D24: $0.01/mo amortized
A25: Heavy user | B25: Reads ~2K, generates ~600 | C25: ~2,600/qtr | D25: $0.02/mo amortized
B27: ROLLING WINDOW (LONG-TERM SCALING)
A28: Rule | B28: After 6 months, older week cards get archived. Quarterly portraits replace them as canonical record.
A29: AI always reads: | B29: Current month micro-summaries (raw) + current quarter week cards + all-time monthly portraits + archived season portraits
A30: Max context cap | B30: Keeps window at ~20-25K tokens even for power users at year 2+ | C30: 20-25K max | D30: ~$0.08/Sonnet call
B32: 4-MONTH COST PROJECTION
B33: Light User (skips days, short replies) | C33: Heavy User (daily, verbose)
A34: Stored context at Month 4 | B34: ~4,800 tokens | C34: ~15,850 tokens
A35: Monthly AI cost | B35: $0.05-0.08/mo | C35: $0.15-0.20/mo
A36: 4-month AI total | B36: $0.20-0.32 | C36: $0.60-0.80
B38: TOTAL OPERATING COSTS
A39: SMS (Twilio) | B39: 1 outbound/day + inbound replies, US | D39: $1.50-2.00/mo
A40: Database (Supabase/PG) | B40: Micro-summaries, week cards, portraits, raw text | D40: $0.001/mo
A41: AI Processing | B41: Range across user types | D41: $0.05-0.20/mo
A42: TOTAL PER USER | D42: $1.60-2.25/mo
B44: BUSINESS MODEL
A45: Subscription Price | B45: $4.99/mo or $39.99/yr | D45: $4.99/mo
A46: Gross Margin | D46: ~55-68%
A47: Break-even users (at $50/mo infra) | D47: ~15-20 subscribers
